{ "compressionlevel":-1,
 "height":20,
 "infinite":false,
 "layers":[
        {
         "data":[0, 0, 0, 0, 0, 0, 0, 0, 0, 0, 0, 0, 0, 0, 0, 0, 0, 0, 0, 0, 0, 0, 0, 0, 0, 0, 0, 0, 0, 0, 0, 0, 0, 0, 0, 0, 0, 0, 0, 0, 0, 0, 0, 0, 0, 0, 0, 0, 0, 0, 0, 0, 0, 0, 0, 0, 0, 0, 0, 0, 0, 0, 0, 0, 0, 0, 0, 0, 0, 0, 0, 0, 0, 0, 0, 0, 0, 0, 0, 0, 0, 0, 0, 0, 0, 0, 0, 0, 0, 0, 0, 0, 0, 0, 0, 0, 0, 0, 0, 0, 0, 0, 0, 0, 0, 0, 0, 0, 0, 0, 0, 0, 0, 0, 0, 0, 0, 0, 0, 0, 0, 0, 0, 0, 0, 0, 0, 0, 0, 0, 0, 0, 0, 0, 0, 0, 0, 0, 0, 0, 0, 0, 0, 0, 0, 0, 0, 0, 0, 0, 0, 0, 0, 0, 0, 0, 0, 0, 0, 0, 0, 0, 0, 0, 0, 0, 0, 0, 0, 0, 0, 0, 0, 0, 0, 0, 0, 0, 0, 0, 0, 0, 0, 0, 0, 0, 0, 0, 0, 0, 0, 0, 0, 0, 0, 0, 0, 0, 0, 0, 0, 0, 0, 0, 0, 0, 0, 0, 0, 0, 0, 0, 0, 0, 0, 0, 0, 0, 0, 0, 0, 0, 0, 0, 0, 0, 0, 0, 0, 0, 0, 0, 0, 0, 0, 0, 0, 0, 0, 0, 0, 0, 0, 0, 0, 0, 0, 0, 0, 0, 0, 0, 0, 0, 0, 0, 0, 0, 0, 0, 0, 0, 0, 0, 0, 0, 0, 0, 0, 0, 0, 0, 0, 0, 0, 0, 0, 0, 0, 0, 0, 0, 0, 0, 0, 0, 0, 0, 0, 0, 0, 0, 0, 0, 0, 0, 0, 0, 0, 0, 0, 0, 0, 0, 0, 0, 151, 0, 0, 151, 0, 0, 0, 0, 151, 0, 0, 0, 0, 0, 1, 25, 25, 1, 25, 25, 25, 1, 25, 1, 1, 25, 1, 25, 1, 1, 1, 1, 1, 25, 1, 1, 1, 1, 1, 25, 1, 25, 25, 1, 25, 25, 1, 25, 25, 25, 1, 25, 25, 1, 1, 1, 1, 25, 1, 25, 1, 25, 25, 1, 25, 25, 25, 25, 25, 25, 25, 25, 25, 1, 25, 25, 25, 25, 1, 1, 1, 25, 1, 25, 1, 25, 1, 1, 25, 25, 1, 1, 1, 25],
         "height":20,
         "id":1,
         "name":"Interactive",
         "opacity":1,
         "type":"tilelayer",
         "visible":true,
         "width":20,
         "x":0,
         "y":0
        }],
 "nextlayerid":2,
 "nextobjectid":1,
 "orientation":"orthogonal",
 "renderorder":"right-down",
 "tiledversion":"1.7.2",
 "tileheight":16,
 "tilesets":[
        {
         "columns":24,
         "firstgid":1,
         "image":"..\/..\/..\/CleanedTileSet.png",
         "imageheight":256,
         "imagewidth":384,
         "margin":0,
         "name":"tileset",
         "spacing":0,
         "tilecount":384,
         "tileheight":16,
         "tilewidth":16,
         "wangsets":[
                {
                 "colors":[
                        {
                         "color":"#ff0000",
                         "name":"",
                         "probability":1,
                         "tile":-1
                        }],
                 "name":"Unnamed Set",
                 "tile":-1,
                 "type":"corner",
                 "wangtiles":[
                        {
                         "tileid":0,
                         "wangid":[0, 1, 0, 1, 0, 1, 0, 1]
                        }, 
                        {
                         "tileid":1,
                         "wangid":[0, 0, 0, 0, 0, 0, 0, 1]
                        }, 
                        {
                         "tileid":24,
                         "wangid":[0, 1, 0, 1, 0, 1, 0, 1]
                        }]
                }]
        }],
 "tilewidth":16,
 "type":"map",
 "version":"1.6",
 "width":20
}